oodb.py
oodb-1.0.3.dist-info/LICENSE
oodb-1.0.3.dist-info/WHEEL
oodb-1.0.3.dist-info/METADATA
oodb-1.0.3.dist-info/RECORD
