Metadata-Version: 2.1
Name: oodb
Version: 1.0.3
Summary: 面向对象数据库 —— 引入了 Python 中类的特性，如：继承、重写、方法、动态属性等。
Keywords: OODBMS,OODBS,oodb
Author-email: 江南雨上 <lcctoor@outlook.com>
Classifier: License :: OSI Approved :: Apache Software License
Requires-Dist: arts>=2024.7.29
Project-URL: Source, https://github.com/lcctoor/arts/tree/main/arts/oodb
